a2a_registry/__init__.py
a2a_registry/_base.py
a2a_registry/client.py
a2a_registry/mcp_server.py
a2a_registry/models.py
a2a_registry_client-0.0.5.dist-info/METADATA
a2a_registry_client-0.0.5.dist-info/WHEEL
a2a_registry_client-0.0.5.dist-info/entry_points.txt
a2a_registry_client-0.0.5.dist-info/top_level.txt
a2a_registry_client-0.0.5.dist-info/RECORD
