Metadata-Version: 2.4
Name: a2a-registry-client
Version: 0.0.5
Summary: Python client library for the A2A Registry
Author-email: A2A Registry Community <contact@a2aregistry.org>
License: MIT
Project-URL: Homepage, https://www.a2aregistry.org
Project-URL: Documentation, https://github.com/prassanna-ravishankar/a2a-registry
Project-URL: Repository, https://github.com/prassanna-ravishankar/a2a-registry
Project-URL: Issues, https://github.com/prassanna-ravishankar/a2a-registry/issues
Keywords: a2a,agents,ai,registry,protocol
Classifier: Development Status :: 3 - Alpha
Classifier: Intended Audience :: Developers
Classifier: License :: OSI Approved :: MIT License
Classifier: Programming Language :: Python :: 3
Classifier: Programming Language :: Python :: 3.10
Classifier: Programming Language :: Python :: 3.11
Classifier: Programming Language :: Python :: 3.12
Classifier: Topic :: Software Development :: Libraries :: Python Modules
Classifier: Topic :: Scientific/Engineering :: Artificial Intelligence
Requires-Python: >=3.10
Requires-Dist: requests>=2.31.0
Requires-Dist: pydantic>=2.0.0
Requires-Dist: fastmcp>=2.0.0
Provides-Extra: dev
Requires-Dist: pytest>=7.0.0; extra == "dev"
Requires-Dist: pytest-cov>=4.0.0; extra == "dev"
Requires-Dist: pytest-asyncio>=0.21.0; extra == "dev"
Requires-Dist: black>=23.0.0; extra == "dev"
Requires-Dist: ty>=0.0.1a1; extra == "dev"
Requires-Dist: ruff>=0.1.0; extra == "dev"
Provides-Extra: async
Requires-Dist: aiohttp>=3.8.0; extra == "async"
Provides-Extra: a2a
Requires-Dist: a2a-sdk>=0.3.7; extra == "a2a"
Provides-Extra: all
Requires-Dist: aiohttp>=3.8.0; extra == "all"
Requires-Dist: a2a-sdk>=0.3.7; extra == "all"
